{
  "best_epoch": 284,
  "capacity_name": "xlarge",
  "checkpoint_path": "/home/lucas-perrier/Documents/projects/scaling-piml/runs-simpson/model=piml-simpson/capacity=xlarge/D=256/data_seed=33/train_seed=202/best.pt",
  "config_path": "/home/lucas-perrier/Documents/projects/scaling-piml/runs-simpson/model=piml-simpson/capacity=xlarge/D=256/data_seed=33/train_seed=202/config.yaml",
  "data_root": "/home/lucas-perrier/Documents/projects/scaling-piml/data/data_seed=33",
  "data_seed": 33,
  "dataset_size": 256,
  "device": "cpu",
  "diverged": false,
  "eligible_for_fit": true,
  "failure_reason": "",
  "hidden_widths": [
    256,
    256,
    256
  ],
  "history_path": "/home/lucas-perrier/Documents/projects/scaling-piml/runs-simpson/model=piml-simpson/capacity=xlarge/D=256/data_seed=33/train_seed=202/history.csv",
  "is_physics_informed": true,
  "metrics_path": "/home/lucas-perrier/Documents/projects/scaling-piml/runs-simpson/model=piml-simpson/capacity=xlarge/D=256/data_seed=33/train_seed=202/metrics.json",
  "model_name": "piml-simpson",
  "nan_detected": false,
  "parameter_count": 133380,
  "physics_prior": "simpson",
  "run_dir": "/home/lucas-perrier/Documents/projects/scaling-piml/runs-simpson/model=piml-simpson/capacity=xlarge/D=256/data_seed=33/train_seed=202",
  "runtime_seconds": 5.713820934295654,
  "status": "success",
  "test_mse": 3.1415693229064345e-05,
  "test_rel_l2": 0.0019306419417262077,
  "train_mse": 8.288800927402917e-06,
  "train_rel_l2": 0.0011329750996083021,
  "train_seed": 202,
  "val_mse": 3.104883580817841e-05,
  "val_rel_l2": 0.0017489009769633412
}