{
  "best_epoch": 72,
  "capacity_name": "large",
  "checkpoint_path": "/home/lucas-perrier/Documents/projects/scaling-piml/runs-lambda-sweep/lambda=0.01/model=piml/capacity=large/D=4096/data_seed=22/train_seed=303/best.pt",
  "config_path": "/home/lucas-perrier/Documents/projects/scaling-piml/runs-lambda-sweep/lambda=0.01/model=piml/capacity=large/D=4096/data_seed=22/train_seed=303/config.yaml",
  "data_root": "/home/lucas-perrier/Documents/projects/scaling-piml/data/data_seed=22",
  "data_seed": 22,
  "dataset_size": 4096,
  "device": "cpu",
  "diverged": false,
  "eligible_for_fit": true,
  "failure_reason": "",
  "hidden_widths": [
    256,
    256
  ],
  "history_path": "/home/lucas-perrier/Documents/projects/scaling-piml/runs-lambda-sweep/lambda=0.01/model=piml/capacity=large/D=4096/data_seed=22/train_seed=303/history.csv",
  "is_physics_informed": true,
  "lambda_phys": 0.01,
  "metrics_path": "/home/lucas-perrier/Documents/projects/scaling-piml/runs-lambda-sweep/lambda=0.01/model=piml/capacity=large/D=4096/data_seed=22/train_seed=303/metrics.json",
  "model_name": "piml",
  "nan_detected": false,
  "parameter_count": 67074,
  "run_dir": "/home/lucas-perrier/Documents/projects/scaling-piml/runs-lambda-sweep/lambda=0.01/model=piml/capacity=large/D=4096/data_seed=22/train_seed=303",
  "runtime_seconds": 6.465755224227905,
  "status": "success",
  "test_mse": 1.1127476682304405e-05,
  "test_rel_l2": 0.0016121355583891273,
  "train_mse": 1.2032349332002923e-05,
  "train_rel_l2": 0.0017209321958944201,
  "train_seed": 303,
  "val_mse": 1.2041464287904091e-05,
  "val_rel_l2": 0.0016921303467825055
}